16_Bit_RISC_Processor_Icarus-Verilog_Code/Parameter.v
`ifndef PARAMETER_H_
`define PARAMETER_H_
// fpga4student.com 
// FPGA projects, VHDL projects, Verilog projects 
// Verilog code for RISC Processor 
// Parameter file
`define col 16 // 16 bits instruction memory, data memory
`define row_i 16 // instruction memory, instructions number, this number can be changed. Adding more instructions to verify your design is a good idea.
`define row_d 8 // The number of data in data memory. We only use 8 data. Do not change this number. You can change the value of each data inside test.data file. Total number is fixed at 8. 
`define filename "./test/50001111_50001212.o"
`define simulation_time #160
`define RESET_WIDTH 1

`endif

16_Bit_RISC_Processor_Icarus-Verilog_Code/ControlUnit.v
`timescale 1ns / 1ps
// fpga4student.com 
// FPGA projects, VHDL projects, Verilog projects 
// Verilog code for RISC Processor 
// Verilog code for Control Unit 
module Control_Unit(
      input[3:0] opcode,
      output reg[1:0] alu_op,
      output reg jump,beq,bne,mem_read,mem_write,alu_src,reg_dst,mem_to_reg,reg_write 
    );


always @(*)
begin
 case(opcode) 
 4'b0000:  // LW
   begin
    reg_dst = 1'b0;
    alu_src = 1'b1;
    mem_to_reg = 1'b1;
    reg_write = 1'b1;
    mem_read = 1'b1;
    mem_write = 1'b0;
    beq = 1'b0;
    bne = 1'b0;
    alu_op = 2'b10;
    jump = 1'b0;   
   end
 4'b0001:  // SW
   begin
    reg_dst = 1'b0;
    alu_src = 1'b1;
    mem_to_reg = 1'b0;
    reg_write = 1'b0;
    mem_read = 1'b0;
    mem_write = 1'b1;
    beq = 1'b0;
    bne = 1'b0;
    alu_op = 2'b10;
    jump = 1'b0;   
   end
 4'b0010:  // data_processing
   begin
    reg_dst = 1'b1;
    alu_src = 1'b0;
    mem_to_reg = 1'b0;
    reg_write = 1'b1;
    mem_read = 1'b0;
    mem_write = 1'b0;
    beq = 1'b0;
    bne = 1'b0;
    alu_op = 2'b00;
    jump = 1'b0;   
   end
 4'b0011:  // data_processing
   begin
    reg_dst = 1'b1;
    alu_src = 1'b0;
    mem_to_reg = 1'b0;
    reg_write = 1'b1;
    mem_read = 1'b0;
    mem_write = 1'b0;
    beq = 1'b0;
    bne = 1'b0;
    alu_op = 2'b00;
    jump = 1'b0;   
   end
 4'b0100:  // data_processing
   begin
    reg_dst = 1'b1;
    alu_src = 1'b0;
    mem_to_reg = 1'b0;
    reg_write = 1'b1;
    mem_read = 1'b0;
    mem_write = 1'b0;
    beq = 1'b0;
    bne = 1'b0;
    alu_op = 2'b00;
    jump = 1'b0;   
   end
 4'b0101:  // data_processing
   begin
    reg_dst = 1'b1;
    alu_src = 1'b0;
    mem_to_reg = 1'b0;
    reg_write = 1'b1;
    mem_read = 1'b0;
    mem_write = 1'b0;
    beq = 1'b0;
    bne = 1'b0;
    alu_op = 2'b00;
    jump = 1'b0;   
   end
 4'b0110:  // data_processing
   begin
    reg_dst = 1'b1;
    alu_src = 1'b0;
    mem_to_reg = 1'b0;
    reg_write = 1'b1;
    mem_read = 1'b0;
    mem_write = 1'b0;
    beq = 1'b0;
    bne = 1'b0;
    alu_op = 2'b00;
    jump = 1'b0;   
   end
 4'b0111:  // data_processing
   begin
    reg_dst = 1'b1;
    alu_src = 1'b0;
    mem_to_reg = 1'b0;
    reg_write = 1'b1;
    mem_read = 1'b0;
    mem_write = 1'b0;
    beq = 1'b0;
    bne = 1'b0;
    alu_op = 2'b00;
    jump = 1'b0;   
   end
 4'b1000:  // data_processing
   begin
    reg_dst = 1'b1;
    alu_src = 1'b0;
    mem_to_reg = 1'b0;
    reg_write = 1'b1;
    mem_read = 1'b0;
    mem_write = 1'b0;
    beq = 1'b0;
    bne = 1'b0;
    alu_op = 2'b00;
    jump = 1'b0;   
   end
 4'b1001:  // data_processing
   begin
    reg_dst = 1'b1;
    alu_src = 1'b0;
    mem_to_reg = 1'b0;
    reg_write = 1'b1;
    mem_read = 1'b0;
    mem_write = 1'b0;
    beq = 1'b0;
    bne = 1'b0;
    alu_op = 2'b00;
    jump = 1'b0;   
   end
  4'b1010:  // added instruction SET 
   begin
    reg_dst = 1'b1;
    alu_src = 1'b0;
    mem_to_reg = 1'b0;
    reg_write = 1'b1;
    mem_read = 1'b0;
    mem_write = 1'b0;
    beq = 1'b0;
    bne = 1'b0;
    alu_op = 2'b00;
    jump = 1'b0;   
   end 
 4'b1011:  // BEQ
   begin
    reg_dst = 1'b0;
    alu_src = 1'b0;
    mem_to_reg = 1'b0;
    reg_write = 1'b0;
    mem_read = 1'b0;
    mem_write = 1'b0;
    beq = 1'b1;
    bne = 1'b0;
    alu_op = 2'b01;
    jump = 1'b0;   
   end
 4'b1100:  // BNE
   begin
    reg_dst = 1'b0;
    alu_src = 1'b0;
    mem_to_reg = 1'b0;
    reg_write = 1'b0;
    mem_read = 1'b0;
    mem_write = 1'b0;
    beq = 1'b0;
    bne = 1'b1;
    alu_op = 2'b01;
    jump = 1'b0;   
   end
 4'b1101:  // J
   begin
    reg_dst = 1'b0;
    alu_src = 1'b0;
    mem_to_reg = 1'b0;
    reg_write = 1'b0;
    mem_read = 1'b0;
    mem_write = 1'b0;
    beq = 1'b0;
    bne = 1'b0;
    alu_op = 2'b00;
    jump = 1'b1;   
   end 
 default: begin
    reg_dst = 1'b1;
    alu_src = 1'b0;
    mem_to_reg = 1'b0;
    reg_write = 1'b1;
    mem_read = 1'b0;
    mem_write = 1'b0;
    beq = 1'b0;
    bne = 1'b0;
    alu_op = 2'b00;
    jump = 1'b0; 
   end
 endcase
 end

endmodule

16_Bit_RISC_Processor_Icarus-Verilog_Code/DataMemory.v
`timescale 1ns / 1ps
`include "Parameter.v"
// fpga4student.com 
// FPGA projects, VHDL projects, Verilog projects 
// Verilog code for RISC Processor 
// Verilog code for data Memory
module Data_Memory(
 input clk,
 input reset,
 // address input, shared by read and write port
 input [15:0]   mem_access_addr,
 
 // write port
 input [15:0]   mem_write_data,
 input     mem_write_en,
 input mem_read,
 // read port
 output [15:0]   mem_read_data
);

reg [`col - 1:0] memory [0:`row_d - 1];
integer f;
wire [2:0] ram_addr=mem_access_addr[2:0];
initial
 begin
  $readmemb("./test/test.data", memory);
 /* 
  f = $fopen(`filename);
 
  $fmonitor(f, "time = %d\n", $time, 
  "\tmemory[0] = %b\n", memory[0],   
  "\tmemory[1] = %b\n", memory[1],
  "\tmemory[2] = %b\n", memory[2],
  "\tmemory[3] = %b\n", memory[3],
  "\tmemory[4] = %b\n", memory[4],
  "\tmemory[5] = %b\n", memory[5],
  "\tmemory[6] = %b\n", memory[6],
  "\tmemory[7] = %b\n", memory[7]);
  */
  `simulation_time;
  $writememb("./test/test_data_result.txt", memory);
 // $fclose(f);
 end
 
 always @(posedge clk ) begin
  if (mem_write_en)
   memory[ram_addr] <= mem_write_data;
 end
 assign mem_read_data = (mem_read==1'b1) ? memory[ram_addr]: 16'd0; 

endmodule

16_Bit_RISC_Processor_Icarus-Verilog_Code/ALU.v
// fpga4student.com 
// FPGA projects, VHDL projects, Verilog projects 
// Verilog code for RISC Processor 
// Verilog code for ALU
module ALU(
 input  [15:0] a,  //src1
 input  [15:0] b,  //src2
 input  [3:0] alu_control, //function sel
 
 output reg [15:0] result,  //result 
 output zero
    );

always @(*)
begin 
 case(alu_control)
 4'b0000: result = a + b; // add
 4'b0001: result = a - b; // sub
 4'b0010: result = ~a;
 4'b0011: result = a<<b;
 4'b0100: result = a>>b;
 4'b0101: result = a & b; // and
 4'b0110: result = a | b; // or
 4'b0111: begin if (a<b) result = 16'd1;
    else result = 16'd0;
    end
 4'b1000: begin if (a>b) result = 16'd8; // added instruction
    else result = 16'd9;
    end
 default:result = a + b; // add
 endcase
end
assign zero = (result==16'd0) ? 1'b1: 1'b0;
 
endmodule

16_Bit_RISC_Processor_Icarus-Verilog_Code/ALUControlUnit.v
`timescale 1ns / 1ps

//fpga4student.com: FPGA projects, Verilog projects, VHDL projects
// Verilog code for 16-bit RISC processor
// ALU_Control Verilog code

module alu_control(
  output reg [3:0] ALU_Cnt,
  input [1:0] ALUOp,
  input [3:0] Opcode
);

  wire [5:0] ALUControlIn;
  assign ALUControlIn = {ALUOp, Opcode};

  always @(ALUControlIn) begin
    case (ALUControlIn)
      6'b10xxxx: ALU_Cnt = 4'b0000;
      6'b01xxxx: ALU_Cnt = 4'b0001;
      6'b000010: ALU_Cnt = 4'b0000;
      6'b000011: ALU_Cnt = 4'b0001;
      6'b000100: ALU_Cnt = 4'b0010;
      6'b000101: ALU_Cnt = 4'b0011;
      6'b000110: ALU_Cnt = 4'b0100;
      6'b000111: ALU_Cnt = 4'b0101;
      6'b001000: ALU_Cnt = 4'b0110;
      6'b001001: ALU_Cnt = 4'b0111;
      6'b001010: ALU_Cnt = 4'b1000; //added instruction
      default: ALU_Cnt = 4'b0000;
    endcase
  end

endmodule

16_Bit_RISC_Processor_Icarus-Verilog_Code/RegisterFile.v
`timescale 1ns / 1ps
// fpga4student.com 
// FPGA projects, VHDL projects, Verilog projects 
// Verilog code for RISC Processor 
// Verilog code for register file
module GPRs(
    input    clk,
    input    reset,
    // write port
    input    reg_write_en,
    input  [2:0] reg_write_dest,
    input  [15:0] reg_write_data,
    //read port 1
    input  [2:0] reg_read_addr_1,
    output  [15:0] reg_read_data_1,
    //read port 2
    input  [2:0] reg_read_addr_2,
    output  [15:0] reg_read_data_2
);
    reg [15:0] reg_array [0:7];
    integer i;

    wire[15:0] reg0;
    wire[15:0] reg1;
    wire[15:0] reg2;
    wire[15:0] reg3;
    wire[15:0] reg4;
    wire[15:0] reg5;
    wire[15:0] reg6;
    wire[15:0] reg7;
    assign reg0 = reg_array[0];
    assign reg1 = reg_array[1];
    assign reg2 = reg_array[2];
    assign reg3 = reg_array[3];
    assign reg4 = reg_array[4];
    assign reg5 = reg_array[5];
    assign reg6 = reg_array[6];
    assign reg7 = reg_array[7];

    // write port
    always @ (posedge clk or negedge reset) begin
        if(~reset) begin
            for(i=0;i<8;i=i+1) begin
                reg_array[i] <= 16'd0;
            end
        end else if(reg_write_en) begin
            reg_array[reg_write_dest] <= reg_write_data;
        end
    end

    assign reg_read_data_1 = reg_array[reg_read_addr_1];
    assign reg_read_data_2 = reg_array[reg_read_addr_2];
endmodule

16_Bit_RISC_Processor_Icarus-Verilog_Code/InstructionMemory.v
`timescale 1ns / 1ps
`include "Parameter.v"
// fpga4student.com 
// FPGA projects, VHDL projects, Verilog projects 
// Verilog code for RISC Processor 
// Verilog code for Instruction Memory
module Instruction_Memory(
 input[15:0] pc,
 output[16:0] instruction
);

 reg [`col - 1:0] memory [0:`row_i - 1];
 wire [3 : 0] rom_addr = pc[4 : 1];
 initial
 begin
  $readmemb("./test/test.prog", memory,0,15);
 end
 assign instruction =  memory[rom_addr]; 

endmodule

16_Bit_RISC_Processor_Icarus-Verilog_Code/Datapath.v
`timescale 1ns / 1ps
`include "RegisterFile.v"
`include "InstructionMemory.v"
`include "ALU.v"
`include "ALUControlUnit.v"
`include "DataMemory.v"
// fpga4student.com 
// FPGA projects, VHDL projects, Verilog projects 
// Verilog code for RISC Processor 
// Verilog code for Data Path of the processor
module Datapath_Unit(
 input clk,
 input reset,
 input jump,beq,mem_read,mem_write,alu_src,reg_dst,mem_to_reg,reg_write,bne,
 input[1:0] alu_op,
 output[3:0] opcode
);
 reg  [15:0] pc_current;
 wire [15:0] pc_next,pc2;
 wire [16:0] instr;
 wire [2:0] reg_write_dest;
 wire [15:0] reg_write_data;
 wire [2:0] reg_read_addr_1;
 wire [15:0] reg_read_data_1;
 wire [2:0] reg_read_addr_2;
 wire [15:0] reg_read_data_2;
 wire [15:0] ext_im,read_data2;
 wire [3:0] ALU_Control;
 wire [15:0] ALU_out;
 wire zero_flag;
 wire [15:0] PC_j, PC_beq, PC_2beq,PC_2bne,PC_bne;
 wire beq_control;
 wire [12:0] jump_shift;
 wire [15:0] mem_read_data;
 // PC 
 initial begin
  pc_current <= 16'd0;
 end
 always @(posedge clk)
 begin 
   pc_current <= pc_next;
 end
 assign pc2 = pc_current + 16'd2;
 // instruction memory
 Instruction_Memory im(.pc(pc_current),.instruction(instr));
 // jump shift left 2
 assign jump_shift = {instr[11:0],1'b0};
 // multiplexer regdest
 assign reg_write_dest = (reg_dst==1'b1) ? instr[5:3] :instr[8:6];
 // register file
 assign reg_read_addr_1 = instr[11:9];
 assign reg_read_addr_2 = instr[8:6];

 // GENERAL PURPOSE REGISTERs
 GPRs reg_file
 (
  .clk(clk),
  .reset(reset),
  .reg_write_en(reg_write),
  .reg_write_dest(reg_write_dest),
  .reg_write_data(reg_write_data),
  .reg_read_addr_1(reg_read_addr_1),
  .reg_read_data_1(reg_read_data_1),
  .reg_read_addr_2(reg_read_addr_2),
  .reg_read_data_2(reg_read_data_2)
 );
 // immediate extend
 assign ext_im = {{10{instr[5]}},instr[5:0]};  
 // ALU control unit
 alu_control ALU_Control_unit(.ALUOp(alu_op),.Opcode(instr[15:12]),.ALU_Cnt(ALU_Control));
 // multiplexer alu_src
 assign read_data2 = (alu_src==1'b1) ? ext_im : reg_read_data_2;
 // ALU 
 ALU alu_unit(.a(reg_read_data_1),.b(read_data2),.alu_control(ALU_Control),.result(ALU_out),.zero(zero_flag));
 // PC beq add
 assign PC_beq = pc2 + {ext_im[14:0],1'b0};
 assign PC_bne = pc2 + {ext_im[14:0],1'b0};
 // beq control
 assign beq_control = beq & zero_flag;
 assign bne_control = bne & (~zero_flag);
 // PC_beq
 assign PC_2beq = (beq_control==1'b1) ? PC_beq : pc2;
 // PC_bne
 assign PC_2bne = (bne_control==1'b1) ? PC_bne : PC_2beq;
 // PC_j
 assign PC_j = {pc2[15:13],jump_shift};
 // PC_next
 assign pc_next = (jump == 1'b1) ? PC_j :  PC_2bne;

 /// Data memory
  Data_Memory dm
   (
    .clk(clk),
    .reset(reset),
    .mem_access_addr(ALU_out),
    .mem_write_data(reg_read_data_2),
    .mem_write_en(mem_write),
    .mem_read(mem_read),
    .mem_read_data(mem_read_data)
   );
 
 // write back
 assign reg_write_data = (mem_to_reg == 1'b1)?  mem_read_data: ALU_out;
 // output to control unit
 assign opcode = instr[15:12];
endmodule

16_Bit_RISC_Processor_Icarus-Verilog_Code/Processor.v
`timescale 1ns / 1ps
`include "Datapath.v"
`include "ControlUnit.v"
// fpga4student.com 
// FPGA projects, VHDL projects, Verilog projects 
// Verilog code for RISC Processor 

module Risc_16_bit(
 input reset,
 input clk
);
 wire jump,bne,beq,mem_read,mem_write,alu_src,reg_dst,mem_to_reg,reg_write;
 wire[1:0] alu_op;
 wire [3:0] opcode;
 // Datapath
 Datapath_Unit DU
 (
  .clk(clk),
  .reset(reset),
  .jump(jump),
  .beq(beq),
  .mem_read(mem_read),
  .mem_write(mem_write),
  .alu_src(alu_src),
  .reg_dst(reg_dst),
  .mem_to_reg(mem_to_reg),
  .reg_write(reg_write),
  .bne(bne),
  .alu_op(alu_op),
  .opcode(opcode)
 );
 // control unit
 Control_Unit control
 (
  .opcode(opcode),
  .reg_dst(reg_dst),
  .mem_to_reg(mem_to_reg),
  .alu_op(alu_op),
  .jump(jump),
  .bne(bne),
  .beq(beq),
  .mem_read(mem_read),
  .mem_write(mem_write),
  .alu_src(alu_src),
  .reg_write(reg_write)
 );

endmodule

16_Bit_RISC_Processor_Icarus-Verilog_Code/Testbench.v
`timescale 1ns / 1ps
`include "Parameter.v"
`include "Processor.v"
// fpga4student.com 
// FPGA projects, VHDL projects, Verilog projects 
// Verilog code for RISC Processor 
// Verilog testbench code to test the processor
module test_Risc_16_bit;

 // Inputs
 reg clk;
 reg reset;

 // Instantiate the Unit Under Test (UUT)
 Risc_16_bit uut (
  .clk(clk),
  .reset(reset)
 );

 initial 
  begin
    $dumpfile("RISC_16_bit.vcd");
    $dumpvars(0, uut);
    // Apply reset for 2 clock cycles
    reset <= 1;
    clk <= 0;
    reset <= 0;
   `simulation_time;
   $finish;
   $display("Test complete!");
  end

 always 
  begin
   #5 clk = ~clk;
  end

endmodule

16_Bit_RISC_Processor_Icarus-Verilog_Code/RISC_16_bit.vcd
$date
	Mon May  1 19:05:59 2023
$end
$version
	Icarus Verilog
$end
$timescale
	1ps
$end
$scope module test_Risc_16_bit $end
$scope module uut $end
$var wire 1 ! clk $end
$var wire 1 " reset $end
$var wire 1 # reg_write $end
$var wire 1 $ reg_dst $end
$var wire 4 % opcode [3:0] $end
$var wire 1 & mem_write $end
$var wire 1 ' mem_to_reg $end
$var wire 1 ( mem_read $end
$var wire 1 ) jump $end
$var wire 1 * bne $end
$var wire 1 + beq $end
$var wire 1 , alu_src $end
$var wire 2 - alu_op [1:0] $end
$scope module DU $end
$var wire 1 . beq_control $end
$var wire 1 / bne_control $end
$var wire 1 ! clk $end
$var wire 1 " reset $end
$var wire 1 0 zero_flag $end
$var wire 3 1 reg_write_dest [2:0] $end
$var wire 16 2 reg_write_data [15:0] $end
$var wire 1 # reg_write $end
$var wire 16 3 reg_read_data_2 [15:0] $end
$var wire 16 4 reg_read_data_1 [15:0] $end
$var wire 3 5 reg_read_addr_2 [2:0] $end
$var wire 3 6 reg_read_addr_1 [2:0] $end
$var wire 1 $ reg_dst $end
$var wire 16 7 read_data2 [15:0] $end
$var wire 16 8 pc_next [15:0] $end
$var wire 16 9 pc2 [15:0] $end
$var wire 4 : opcode [3:0] $end
$var wire 1 & mem_write $end
$var wire 1 ' mem_to_reg $end
$var wire 16 ; mem_read_data [15:0] $end
$var wire 1 ( mem_read $end
$var wire 13 < jump_shift [12:0] $end
$var wire 1 ) jump $end
$var wire 17 = instr [16:0] $end
$var wire 16 > ext_im [15:0] $end
$var wire 1 * bne $end
$var wire 1 + beq $end
$var wire 1 , alu_src $end
$var wire 2 ? alu_op [1:0] $end
$var wire 16 @ PC_j [15:0] $end
$var wire 16 A PC_bne [15:0] $end
$var wire 16 B PC_beq [15:0] $end
$var wire 16 C PC_2bne [15:0] $end
$var wire 16 D PC_2beq [15:0] $end
$var wire 16 E ALU_out [15:0] $end
$var wire 4 F ALU_Control [3:0] $end
$var reg 16 G pc_current [15:0] $end
$scope module ALU_Control_unit $end
$var wire 4 H Opcode [3:0] $end
$var wire 2 I ALUOp [1:0] $end
$var wire 6 J ALUControlIn [5:0] $end
$var reg 4 K ALU_Cnt [3:0] $end
$upscope $end
$scope module alu_unit $end
$var wire 4 L alu_control [3:0] $end
$var wire 16 M b [15:0] $end
$var wire 1 0 zero $end
$var wire 16 N a [15:0] $end
$var reg 16 O result [15:0] $end
$upscope $end
$scope module dm $end
$var wire 1 ! clk $end
$var wire 16 P mem_access_addr [15:0] $end
$var wire 1 " reset $end
$var wire 3 Q ram_addr [2:0] $end
$var wire 1 & mem_write_en $end
$var wire 16 R mem_write_data [15:0] $end
$var wire 16 S mem_read_data [15:0] $end
$var wire 1 ( mem_read $end
$upscope $end
$scope module im $end
$var wire 16 T pc [15:0] $end
$var wire 4 U rom_addr [3:0] $end
$var wire 17 V instruction [16:0] $end
$upscope $end
$scope module reg_file $end
$var wire 1 ! clk $end
$var wire 16 W reg0 [15:0] $end
$var wire 16 X reg1 [15:0] $end
$var wire 16 Y reg2 [15:0] $end
$var wire 16 Z reg3 [15:0] $end
$var wire 16 [ reg4 [15:0] $end
$var wire 16 \ reg5 [15:0] $end
$var wire 16 ] reg6 [15:0] $end
$var wire 16 ^ reg7 [15:0] $end
$var wire 3 _ reg_read_addr_1 [2:0] $end
$var wire 3 ` reg_read_addr_2 [2:0] $end
$var wire 16 a reg_read_data_1 [15:0] $end
$var wire 16 b reg_read_data_2 [15:0] $end
$var wire 16 c reg_write_data [15:0] $end
$var wire 3 d reg_write_dest [2:0] $end
$var wire 1 " reset $end
$var wire 1 # reg_write_en $end
$var integer 32 e i [31:0] $end
$upscope $end
$upscope $end
$scope module control $end
$var wire 4 f opcode [3:0] $end
$var reg 2 g alu_op [1:0] $end
$var reg 1 , alu_src $end
$var reg 1 + beq $end
$var reg 1 * bne $end
$var reg 1 ) jump $end
$var reg 1 ( mem_read $end
$var reg 1 ' mem_to_reg $end
$var reg 1 & mem_write $end
$var reg 1 $ reg_dst $end
$var reg 1 # reg_write $end
$upscope $end
$upscope $end
$upscope $end
$enddefinitions $end
#0
$dumpvars
b10 g
b0 f
b1000 e
b0 d
b1 c
b0 b
b0 a
b0 `
b10 _
b0 ^
b0 ]
b0 \
b0 [
b0 Z
b0 Y
b0 X
b0 W
b10000000000 V
b0 U
b0 T
b1 S
b0 R
b0 Q
b0 P
b0 O
b0 N
b0 M
b0 L
b0 K
b100000 J
b10 I
b0 H
b0 G
b0 F
b0 E
b10 D
b10 C
b10 B
b10 A
b100000000000 @
b10 ?
b0 >
b10000000000 =
b100000000000 <
b1 ;
b0 :
b10 9
b10 8
b0 7
b10 6
b0 5
b0 4
b0 3
b1 2
b0 1
10
0/
0.
b10 -
1,
0+
0*
0)
1(
1'
0&
b0 %
0$
1#
1"
0!
$end
#1000
0"
#5000
b10 2
b10 c
b10 ;
b10 S
00
b1 Q
b1 E
b1 O
b1 P
b100 8
b1 7
b1 M
b1 1
b1 d
b100 C
b1 >
b1 5
b1 `
b100010000010 @
b100010000010 <
b100 D
b10001000001 =
b10001000001 V
b1 U
b110 B
b110 A
b100 9
b10 G
b10 T
b0 3
b0 R
b0 b
b1 W
1!
#10000
0!
#15000
b11 2
b11 c
b10 1
b10 d
b0 ;
b0 S
b11 Q
b110 8
b0 -
b0 ?
b0 I
b0 g
0(
0'
0,
1$
b10 7
b10 M
b11 E
b11 O
b11 P
b110 C
b10 %
b10 :
b10 f
b10 J
b10 H
b10000 >
b1 4
b1 N
b1 a
b0 6
b0 _
b10100000 @
b10100000 <
b110 D
b10000001010000 =
b10000001010000 V
b10 U
b100110 B
b100110 A
b110 9
b100 G
b100 T
b10 3
b10 R
b10 b
b10 X
1!
#20000
0!
#25000
b10 Q
b10 2
b10 c
b1000 8
b10 -
b10 ?
b10 I
b10 g
1&
0#
1,
0$
b0 7
b0 M
b10 E
b10 O
b10 P
b10 1
b10 d
b1000 C
b1 %
b1 :
b1 f
b100001 J
b1 H
b0 >
b11 3
b11 R
b11 b
b10 5
b10 `
b10 4
b10 N
b10 a
b1 6
b1 _
b10100000000 @
b10100000000 <
b1000 D
b1001010000000 =
b1001010000000 V
b11 U
b1000 B
b1000 A
b1000 9
b110 G
b110 T
b11 Y
1!
#30000
0!
#35000
b1 F
b1 K
b1 L
b111 Q
b1111111111111111 2
b1111111111111111 c
b1010 8
b0 -
b0 ?
b0 I
b0 g
0&
1#
0,
1$
b10 7
b10 M
b1111111111111111 E
b1111111111111111 O
b1111111111111111 P
b10 1
b10 d
b1010 C
b11 %
b11 :
b11 f
b11 J
b11 H
b10000 >
b10 3
b10 R
b10 b
b1 5
b1 `
b1 4
b1 N
b1 a
b0 6
b0 _
b10100000 @
b10100000 <
b1010 D
b11000001010000 =
b11000001010000 V
b100 U
b101010 B
b101010 A
b1010 9
b1000 G
b1000 T
1!
#40000
0!
#45000
b110 Q
b1111111111111110 2
b1111111111111110 c
b1111111111111110 E
b1111111111111110 O
b1111111111111110 P
b1100 8
b10 F
b10 K
b10 L
b1100 C
b100 %
b100 :
b100 f
b100 J
b100 H
b1100 D
b100000001010000 =
b100000001010000 V
b101 U
b101100 B
b101100 A
b1100 9
b1010 G
b1010 T
b1111111111111111 Y
1!
#50000
0!
#55000
b100 Q
b100 2
b100 c
b100 E
b100 O
b100 P
b1110 8
b11 F
b11 K
b11 L
b1110 C
b101 %
b101 :
b101 f
b101 J
b101 H
b1110 D
b101000001010000 =
b101000001010000 V
b110 U
b101110 B
b101110 A
b1110 9
b1100 G
b1100 T
b1111111111111110 Y
1!
#60000
0!
#65000
10
b0 Q
b0 2
b0 c
b0 E
b0 O
b0 P
b10000 8
b100 F
b100 K
b100 L
b10000 C
b110 %
b110 :
b110 f
b110 J
b110 H
b10000 D
b110000001010000 =
b110000001010000 V
b111 U
b110000 B
b110000 A
b10000 9
b1110 G
b1110 T
b100 Y
1!
#70000
0!
#75000
b10010 8
b101 F
b101 K
b101 L
b10010 C
b111 %
b111 :
b111 f
b111 J
b111 H
b10010 D
b111000001010000 =
b111000001010000 V
b1000 U
b110010 B
b110010 A
b10010 9
b10000 G
b10000 T
b0 Y
1!
#80000
0!
#85000
00
b11 Q
b11 2
b11 c
b11 E
b11 O
b11 P
b10100 8
b110 F
b110 K
b110 L
b10100 C
b1000 %
b1000 :
b1000 f
b1000 J
b1000 H
b10100 D
b1000000001010000 =
b1000000001010000 V
b1001 U
b110100 B
b110100 A
b10100 9
b10010 G
b10010 T
1!
#90000
0!
#95000
b1 Q
b1 2
b1 c
b1 E
b1 O
b1 P
b10110 8
b111 F
b111 K
b111 L
b10110 C
b1001 %
b1001 :
b1001 f
b1001 J
b1001 H
b10110 D
b1001000001010000 =
b1001000001010000 V
b1010 U
b110110 B
b110110 A
b10110 9
b10100 G
b10100 T
b11 Y
1!
#100000
0!
#105000
b10 Q
b10 2
b10 c
b10 E
b10 O
b10 P
b11000 8
b0 F
b0 K
b0 L
b1 7
b1 M
b0 1
b0 d
b11000 C
b10 %
b10 :
b10 f
b10 J
b10 H
b0 >
b1 3
b1 R
b1 b
b0 5
b0 `
b0 @
b0 <
b11000 D
b10000000000000 =
b10000000000000 V
b1011 U
b11000 B
b11000 A
b11000 9
b10110 G
b10110 T
b1 Y
1!
#110000
0!
#115000
b1 1
b1 d
b11010 8
b1 -
b1 ?
b1 I
b1 g
1+
0#
0$
b11010 C
b1011 %
b1011 :
b1011 f
b11011 J
b1011 H
b1 >
b1 5
b1 `
b10000010 @
b10000010 <
b100 Q
b100 2
b100 c
b11010 D
b1011000001000001 =
b1011000001000001 V
b1100 U
b100 E
b100 O
b100 P
b10 7
b10 M
b11100 B
b11100 A
b11010 9
b11000 G
b11000 T
b10 4
b10 N
b10 a
b10 3
b10 R
b10 b
b10 W
1!
#120000
0!
#125000
1/
b11100 8
1*
0+
b11100 C
b1100 %
b1100 :
b1100 f
b11100 J
b1100 H
b0 >
b10000000 @
b10000000 <
b11100 D
b1100000001000000 =
b1100000001000000 V
b1101 U
b11100 B
b11100 A
b11100 9
b11010 G
b11010 T
1!
#130000
0!
#135000
0/
1)
b0 -
b0 ?
b0 I
b0 g
0*
b0 1
b0 d
b0 8
b1101 %
b1101 :
b1101 f
b1101 J
b1101 H
b0 5
b0 `
b0 @
b0 <
b11110 C
b11110 D
b1101000000000000 =
b1101000000000000 V
b1110 U
b11110 B
b11110 A
b11110 9
b11100 G
b11100 T
1!
#140000
0!
#145000
b10 ;
b10 S
b0 7
b0 M
b1 Q
b10 2
b10 c
0)
b10 -
b10 ?
b10 I
b10 g
1(
1#
1'
1,
b1 E
b1 O
b1 P
b10 8
b10 C
b0 %
b0 :
b0 f
b100000 J
b0 H
b1 4
b1 N
b1 a
b10 6
b10 _
b100000000000 @
b100000000000 <
b10 D
b10000000000 =
b10000000000 V
b0 U
b10 B
b10 A
b10 9
b0 G
b0 T
1!
#150000
0!
#155000
b11 2
b11 c
b11 ;
b11 S
b10 Q
b10 E
b10 O
b10 P
b100 8
b1 7
b1 M
b1 1
b1 d
b100 C
b1 >
b1 5
b1 `
b100010000010 @
b100010000010 <
b100 D
b10001000001 =
b10001000001 V
b1 U
b110 B
b110 A
b100 9
b10 G
b10 T
1!
